ariamehr_gemini_pandas_agent-0.1.0.dist-info/licenses/LICENSE
ariamehr_gpandas_agent/__init__.py
ariamehr_gpandas_agent/executor.py
ariamehr_gpandas_agent/graph.py
ariamehr_gpandas_agent/prompt.py
ariamehr_gpandas_agent/tools.py
ariamehr_gemini_pandas_agent-0.1.0.dist-info/METADATA
ariamehr_gemini_pandas_agent-0.1.0.dist-info/WHEEL
ariamehr_gemini_pandas_agent-0.1.0.dist-info/top_level.txt
ariamehr_gemini_pandas_agent-0.1.0.dist-info/RECORD
