Metadata-Version: 2.4
Name: ariamehr-gemini-pandas-agent
Version: 0.1.0
Summary: Google‑native alternative to LangChain's create_pandas_dataframe_agent by Ariamehr A
Author-email: Ariamehr A <ariamehr@example.com>
License: MIT License
Keywords: gemini,pandas,agent,langgraph,google-generativeai,ariamehr
Classifier: Programming Language :: Python :: 3
Classifier: License :: OSI Approved :: MIT License
Classifier: Intended Audience :: Developers
Requires-Python: >=3.10
License-File: LICENSE
Requires-Dist: pandas>=2.2
Requires-Dist: google-generativeai>=1.7.0
Requires-Dist: langgraph>=0.3.21
Requires-Dist: typing-extensions>=4.9
Dynamic: license-file
